flexi_dev/__init__.py
flexi_dev/eventdriver.py
flexi_dev/joystickdriver.py
flexi_dev/metadriver.py
flexi_dev/mousedriver.py
flexi_dev-1.1.0.dist-info/LICENSE
flexi_dev-1.1.0.dist-info/METADATA
flexi_dev-1.1.0.dist-info/WHEEL
flexi_dev-1.1.0.dist-info/top_level.txt
flexi_dev-1.1.0.dist-info/RECORD
