Metadata-Version: 2.1
Name: flexi-dev
Version: 1.1.0
Summary: Use standard input devices as novel interaction controllers.
Home-page: https://github.com/mhameed/python_flexi_dev
Author: Mesar Hameed
Author-email: mesar.hameed@gmail.com
License: UNKNOWN
Project-URL: Source, https://github.com/mhameed/python_flexi_dev/
Project-URL: Bug Tracker, https://github.com/mhameed/python_flexi_dev/issues
Platform: UNKNOWN
Classifier: Development Status :: 4 - Beta
Classifier: Intended Audience :: Developers
Classifier: Framework :: Trio
Classifier: License :: OSI Approved :: GNU General Public License v3 (GPLv3)
Classifier: Natural Language :: English
Classifier: Operating System :: POSIX :: Linux
Classifier: Programming Language :: Python
Classifier: Programming Language :: Python :: 3
Classifier: Programming Language :: Python :: 3.7
Classifier: Programming Language :: Python :: 3.8
Classifier: Topic :: Adaptive Technologies
Classifier: Topic :: Software Development :: Libraries
Requires-Python: >=3.7
License-File: LICENSE
Requires-Dist: trio
